piir/__init__.py
piir/cli.py
piir/decode.py
piir/encode.py
piir/io.py
piir/prettify.py
piir/remote.py
piir/util.py
piir/version.py
piir/remotes/hitachi_rar_8p2.py
PiIR-0.2.5.dist-info/LICENSE
PiIR-0.2.5.dist-info/METADATA
PiIR-0.2.5.dist-info/WHEEL
PiIR-0.2.5.dist-info/entry_points.txt
PiIR-0.2.5.dist-info/top_level.txt
PiIR-0.2.5.dist-info/RECORD
