Metadata-Version: 2.1
Name: PiIR
Version: 0.2.5
Summary: IR remote control for Raspberry Pi
Home-page: https://github.com/ts1/PiIR
Author: Takeshi Sone
Author-email: takeshi.sone@gmail.com
License: MIT
Platform: UNKNOWN
Classifier: Environment :: Console
Classifier: Intended Audience :: End Users/Desktop
Classifier: Intended Audience :: Developers
Classifier: Topic :: System :: Hardware
Classifier: Topic :: Home Automation
Classifier: License :: OSI Approved :: MIT License
Classifier: Development Status :: 4 - Beta
Classifier: Programming Language :: Python :: 3 :: Only
Requires-Python: >= 3.6
Requires-Dist: pigpio
